RTS_WebUIBuilder/RAdditions.py
RTS_WebUIBuilder/RBody.py
RTS_WebUIBuilder/RBox.py
RTS_WebUIBuilder/RDocument.py
RTS_WebUIBuilder/RFrame.py
RTS_WebUIBuilder/RGroupStyle.py
RTS_WebUIBuilder/RHead.py
RTS_WebUIBuilder/RImage.py
RTS_WebUIBuilder/RInput.py
RTS_WebUIBuilder/RLabel.py
RTS_WebUIBuilder/RQuickScripts.py
RTS_WebUIBuilder/RStyle.py
RTS_WebUIBuilder/RTitle.py
RTS_WebUIBuilder/RWebserver.py
RTS_WebUIBuilder/RpyColorizer.py
RTS_WebUIBuilder/__init__.py
RTS_WebUIBuilder/cache.py
RTS_WebUIBuilder/exeptional.py
RTS_WebUIBuilder/privatizehead.py
RTS_WebUIBuilder/docs/__init__.py
RTS_WebUIBuilder/docs/load.py
RTS_WebUIBuilder/presets/Button1.py
RTS_WebUIBuilder/presets/__init__.py
RTS_WebUIBuilder-1.1.dist-info/LICENCE
RTS_WebUIBuilder-1.1.dist-info/METADATA
RTS_WebUIBuilder-1.1.dist-info/WHEEL
RTS_WebUIBuilder-1.1.dist-info/top_level.txt
RTS_WebUIBuilder-1.1.dist-info/RECORD
