Metadata-Version: 2.1
Name: RTS-WebUIBuilder
Version: 1.1
Summary: A simple webserver with a simple webui builder.
Home-page: https://github.com/RandomTimeLP/RTS_Webbuilder
Author: RandomTimeTV
Author-email: dergepanzerte1@gmail.com
License: MIT with required credit to the author.
Keywords: WebUIBuilder,Webserver,Work In Progress
Platform: UNKNOWN
Classifier: Development Status :: 3 - Alpha
Classifier: License :: OSI Approved :: MIT License
Classifier: Programming Language :: Python :: 3.6
Classifier: Programming Language :: Python :: 3.7
Classifier: Programming Language :: Python :: 3.8
Classifier: Programming Language :: Python :: 3.9
License-File: LICENCE
Requires-Dist: aiohttp
Requires-Dist: pygments
